streamlit_anywidget/__init__.py
streamlit_anywidget/example.py
streamlit_anywidget/frontend/build/asset-manifest.json
streamlit_anywidget/frontend/build/bootstrap.min.css
streamlit_anywidget/frontend/build/index.html
streamlit_anywidget/frontend/build/static/js/main.883655fe.js
streamlit_anywidget/frontend/build/static/js/main.883655fe.js.LICENSE.txt
streamlit_anywidget/frontend/build/static/js/main.883655fe.js.map
streamlit_anywidget/frontend/build/static/js/main.abed9175.js
streamlit_anywidget/frontend/build/static/js/main.abed9175.js.LICENSE.txt
streamlit_anywidget/frontend/build/static/js/main.abed9175.js.map
streamlit_anywidget-0.1.3.dist-info/LICENSE
streamlit_anywidget-0.1.3.dist-info/METADATA
streamlit_anywidget-0.1.3.dist-info/WHEEL
streamlit_anywidget-0.1.3.dist-info/top_level.txt
streamlit_anywidget-0.1.3.dist-info/RECORD
