Metadata-Version: 2.1
Name: streamlit-anywidget
Version: 0.1.3
Summary: Streamlit component that enables anywidget support.
Home-page: https://github.com/mdrazak2001/streamlit-anywidget
Author: Mohammed Razak
Author-email: mohammedrazak2001@gmail.com
License: UNKNOWN
Project-URL: Homepage, https://github.com/mdrazak2001/streamlit-anywidget
Project-URL: Documentation, https://github.com/mdrazak2001/streamlit-anywidget#readme
Project-URL: Source Code, https://github.com/mdrazak2001/streamlit-anywidget
Platform: UNKNOWN
Classifier: Programming Language :: Python :: 3
Classifier: License :: OSI Approved :: MIT License
Classifier: Operating System :: OS Independent
Requires-Python: >=3.7
License-File: LICENSE
Requires-Dist: anywidget
Requires-Dist: streamlit>=0.63
Provides-Extra: devel
Requires-Dist: playwright==1.48.0; extra == "devel"
Requires-Dist: pytest-playwright-snapshot==1.0; extra == "devel"
Requires-Dist: pytest-rerunfailures==12.0; extra == "devel"
Requires-Dist: pytest==7.4.0; extra == "devel"
Requires-Dist: requests==2.31.0; extra == "devel"
Requires-Dist: wheel; extra == "devel"
